<?xml version="1.0" encoding="Windows-1252"?>
<Path xmlns:xsi="http://www.w3.org/2001/XMLSchema-instance" xmlns:xsd="http://www.w3.org/2001/XMLSchema">
  <Name>VolcanicIsland_Sp3Ex2</Name>
  <EntryGate>Spawn3</EntryGate>
  <ExitGate>ExitGate2</ExitGate>
  <Commercial>28.1648159</Commercial>
  <Light>49.28843</Light>
  <Priority>39.43074</Priority>
  <Nodes>
    <Node>
      <Name>StartNode</Name>
      <posX>-98.1</posX>
      <posY>17.5</posY>
      <posZ>-8.1</posZ>
      <commercial>0</commercial>
      <light>0</light>
      <priority>0</priority>
      <speedModifier>0</speedModifier>
    </Node>
    <Node>
      <Name>Node1</Name>
      <posX>-83.11853</posX>
      <posY>17.5</posY>
      <posZ>-8.845462</posZ>
      <commercial>2.14285779</commercial>
      <light>3.750001</light>
      <priority>3.00000072</priority>
      <speedModifier>3.00000072</speedModifier>
    </Node>
    <Node>
      <Name>Node2</Name>
      <posX>-68.13706</posX>
      <posY>17.5</posY>
      <posZ>-9.590923</posZ>
      <commercial>4.28571558</commercial>
      <light>7.500002</light>
      <priority>6.00000143</priority>
      <speedModifier>6.00000143</speedModifier>
    </Node>
    <Node>
      <Name>Node3</Name>
      <posX>-53.1555977</posX>
      <posY>17.5</posY>
      <posZ>-10.3363848</posZ>
      <commercial>6.42857265</commercial>
      <light>11.2500019</light>
      <priority>9.000001</priority>
      <speedModifier>9.000001</speedModifier>
    </Node>
    <Node>
      <Name>Node4</Name>
      <posX>-38.1741333</posX>
      <posY>17.5</posY>
      <posZ>-11.0818462</posZ>
      <commercial>8.57143</commercial>
      <light>15.0000019</light>
      <priority>12.000001</priority>
      <speedModifier>12.000001</speedModifier>
    </Node>
    <Node>
      <Name>Node5</Name>
      <posX>-23.1926689</posX>
      <posY>17.5</posY>
      <posZ>-11.8273077</posZ>
      <commercial>10.7142868</commercial>
      <light>18.7500019</light>
      <priority>15.000001</priority>
      <speedModifier>15.000001</speedModifier>
    </Node>
    <Node>
      <Name>Node6</Name>
      <posX>-8.211204</posX>
      <posY>17.5</posY>
      <posZ>-12.5727682</posZ>
      <commercial>12.8571444</commercial>
      <light>22.5000019</light>
      <priority>18.0000019</priority>
      <speedModifier>18.0000019</speedModifier>
    </Node>
    <Node>
      <Name>Node7</Name>
      <posX>6.770261</posX>
      <posY>17.5</posY>
      <posZ>-13.31823</posZ>
      <commercial>15.0000019</commercial>
      <light>26.2500019</light>
      <priority>21.0000019</priority>
      <speedModifier>21.0000019</speedModifier>
    </Node>
    <Node>
      <Name>Node8</Name>
      <posX>21.7517262</posX>
      <posY>17.5</posY>
      <posZ>-14.06369</posZ>
      <commercial>17.1428585</commercial>
      <light>30.0000019</light>
      <priority>24.0000019</priority>
      <speedModifier>24.0000019</speedModifier>
    </Node>
    <Node>
      <Name>Node9</Name>
      <posX>36.7331924</posX>
      <posY>17.5</posY>
      <posZ>-14.8091516</posZ>
      <commercial>19.2857151</commercial>
      <light>33.7500038</light>
      <priority>27.0000019</priority>
      <speedModifier>27.0000019</speedModifier>
    </Node>
    <Node>
      <Name>Node10</Name>
      <posX>51.7146568</posX>
      <posY>17.5</posY>
      <posZ>-15.5546131</posZ>
      <commercial>21.4285717</commercial>
      <light>37.5000038</light>
      <priority>30.0000019</priority>
      <speedModifier>30.0000019</speedModifier>
    </Node>
    <Node>
      <Name>Node11</Name>
      <posX>66.69612</posX>
      <posY>17.5</posY>
      <posZ>-16.3000736</posZ>
      <commercial>23.5714283</commercial>
      <light>41.2500038</light>
      <priority>33</priority>
      <speedModifier>33</speedModifier>
    </Node>
    <Node>
      <Name>Node12</Name>
      <posX>81.67759</posX>
      <posY>17.5</posY>
      <posZ>-17.0455341</posZ>
      <commercial>25.7142868</commercial>
      <light>45.0000038</light>
      <priority>36</priority>
      <speedModifier>36</speedModifier>
    </Node>
    <Node>
      <Name>Node13</Name>
      <posX>98.81</posX>
      <posY>17.5</posY>
      <posZ>-17.9</posZ>
      <commercial>28.1648159</commercial>
      <light>49.28843</light>
      <priority>39.43074</priority>
      <speedModifier>39.43074</speedModifier>
    </Node>
  </Nodes>
</Path>